myrollingforecastpackage/__init__.py
myrollingforecastpackage/demo.py
myrollingforecastpackage-1.0.0.dist-info/DESCRIPTION.rst
myrollingforecastpackage-1.0.0.dist-info/METADATA
myrollingforecastpackage-1.0.0.dist-info/RECORD
myrollingforecastpackage-1.0.0.dist-info/WHEEL
myrollingforecastpackage-1.0.0.dist-info/entry_points.txt
myrollingforecastpackage-1.0.0.dist-info/metadata.json
myrollingforecastpackage-1.0.0.dist-info/top_level.txt
